drf_extensions-0.8.0.dist-info/licenses/AUTHORS.md
drf_extensions-0.8.0.dist-info/licenses/LICENSE
rest_framework_extensions/__init__.py
rest_framework_extensions/compat.py
rest_framework_extensions/decorators.py
rest_framework_extensions/exceptions.py
rest_framework_extensions/fields.py
rest_framework_extensions/mixins.py
rest_framework_extensions/permissions.py
rest_framework_extensions/routers.py
rest_framework_extensions/serializers.py
rest_framework_extensions/settings.py
rest_framework_extensions/test.py
rest_framework_extensions/utils.py
rest_framework_extensions/bulk_operations/__init__.py
rest_framework_extensions/bulk_operations/mixins.py
rest_framework_extensions/cache/__init__.py
rest_framework_extensions/cache/decorators.py
rest_framework_extensions/cache/mixins.py
rest_framework_extensions/etag/__init__.py
rest_framework_extensions/etag/decorators.py
rest_framework_extensions/etag/mixins.py
rest_framework_extensions/key_constructor/__init__.py
rest_framework_extensions/key_constructor/bits.py
rest_framework_extensions/key_constructor/constructors.py
drf_extensions-0.8.0.dist-info/METADATA
drf_extensions-0.8.0.dist-info/WHEEL
drf_extensions-0.8.0.dist-info/top_level.txt
drf_extensions-0.8.0.dist-info/RECORD
